visible_to_sqlite/__init__.py
visible_to_sqlite/cli.py
visible_to_sqlite/utils.py
visible_to_sqlite-1.0.0.dist-info/LICENSE
visible_to_sqlite-1.0.0.dist-info/METADATA
visible_to_sqlite-1.0.0.dist-info/WHEEL
visible_to_sqlite-1.0.0.dist-info/entry_points.txt
visible_to_sqlite-1.0.0.dist-info/top_level.txt
visible_to_sqlite-1.0.0.dist-info/RECORD
