Metadata-Version: 2.1
Name: visible-to-sqlite
Version: 1.0.0
Summary: Convert exported CSV from Visible app to a SQLite DB
Author: Avner Shanan
License: Apache License, Version 2.0
License-File: LICENSE
Requires-Dist: Click
Requires-Dist: sqlite-utils
